ndsafe.py
ndsafe-0.1.0.dist-info/LICENSE
ndsafe-0.1.0.dist-info/METADATA
ndsafe-0.1.0.dist-info/WHEEL
ndsafe-0.1.0.dist-info/RECORD
