Metadata-Version: 2.1
Name: ndsafe
Version: 0.1.0
Summary: A NumPy-compatible array that ensures shape safety and prevents silent.errors.
Author: Lucian Ursu
Author-email: lucian.ursu@gmail.com
Requires-Python: >=3.11,<4.0
Classifier: Programming Language :: Python :: 3
Classifier: Programming Language :: Python :: 3.11
Classifier: Programming Language :: Python :: 3.12
Requires-Dist: numpy (>=2.2.2,<3.0.0)
